raster_extraction_tool/__init__.py
raster_extraction_tool/example_run.py
raster_extraction_tool/helper_functions.py
raster_extraction_tool/main.py
raster_extraction_tool/raster_extraction_functions.py
raster_extraction_tool-0.1.2.dist-info/METADATA
raster_extraction_tool-0.1.2.dist-info/WHEEL
raster_extraction_tool-0.1.2.dist-info/top_level.txt
raster_extraction_tool-0.1.2.dist-info/RECORD
