Metadata-Version: 2.1
Name: raster-extraction-tool
Version: 0.1.2
Summary: Extract raster data at input coordinates. Meant for processing many rasters at once.
Home-page: https://github.com/UtrechtUniversity/raster_extraction
Author: L. Roga
Author-email: l.q.roga@uu.nl
Classifier: Programming Language :: Python :: 3
Classifier: License :: OSI Approved :: MIT License
Classifier: Operating System :: OS Independent
Requires-Python: >=3.11
Requires-Dist: numpy==1.26.4
Requires-Dist: pandas
Requires-Dist: pyproj
